git_list_authors/__init__.py
git_list_authors/__main__.py
git_list_authors/main.py
git_list_authors-0.1.dist-info/LICENSES/CC0-1.0.txt
git_list_authors-0.1.dist-info/LICENSES/GPL-3.0-or-later.txt
git_list_authors-0.1.dist-info/METADATA
git_list_authors-0.1.dist-info/WHEEL
git_list_authors-0.1.dist-info/entry_points.txt
git_list_authors-0.1.dist-info/RECORD
