Metadata-Version: 2.1
Name: git-list-authors
Version: 0.1
Summary: Git plugin for listing authors of all commits by file.
Author: Michael Pöhn
Author-email: michael@poehn.at
Requires-Python: >=3.7,<4.0
Classifier: Programming Language :: Python :: 3
Classifier: Programming Language :: Python :: 3.7
Classifier: Programming Language :: Python :: 3.8
Classifier: Programming Language :: Python :: 3.9
Classifier: Programming Language :: Python :: 3.10
Classifier: Programming Language :: Python :: 3.11
